examples/stocks_for_trading_view_example.csv
examples/usage.py
financial_scraper/__init__.py
financial_scraper/config/__init__.py
financial_scraper/config/selenium.py
financial_scraper/config/utils.py
financial_scraper/providers/__init__.py
financial_scraper/providers/fundamentus.py
financial_scraper/providers/investor_ten.py
financial_scraper/providers/market_data.py
financial_scraper/providers/status_invest.py
financial_scraper/providers/trading_view.py
services/__init__.py
services/funds_explorer.py
services/investor_ten.py
services/market_data.py
services/service.py
services/settings.py
services/trading_view.py
financial_scraper-1.1.0.dist-info/METADATA
financial_scraper-1.1.0.dist-info/WHEEL
financial_scraper-1.1.0.dist-info/entry_points.txt
financial_scraper-1.1.0.dist-info/licenses/LICENSE
financial_scraper-1.1.0.dist-info/RECORD
