Metadata-Version: 2.4
Name: financial-scraper
Version: 1.1.0
Summary: A Python-based web scraping tool for collecting financial data from multiple sources
License-File: LICENSE
Keywords: finance,scraping,stocks,brazil,investing
Author: João Pedro Limão
Author-email: jplimao077@gmail.com
Requires-Python: >=3.10,<4.0
Classifier: Development Status :: 4 - Beta
Classifier: Intended Audience :: Financial and Insurance Industry
Classifier: License :: OSI Approved :: MIT License
Classifier: Programming Language :: Python :: 3
Classifier: Programming Language :: Python :: 3.10
Classifier: Programming Language :: Python :: 3.11
Classifier: Programming Language :: Python :: 3.12
Classifier: Programming Language :: Python :: 3.13
Classifier: Programming Language :: Python :: 3.14
Classifier: Topic :: Office/Business :: Financial :: Investment
Requires-Dist: beautifulsoup4 (>=4.13.4,<5.0.0)
Requires-Dist: lxml-html-clean (>=0.4.2,<0.5.0)
Requires-Dist: lxml[html-clean] (>=6.0.1,<7.0.0)
Requires-Dist: pandas (>=2.3.2,<3.0.0)
Requires-Dist: requests (>=2.32.5,<3.0.0)
Requires-Dist: requests-html (>=0.10.0,<0.11.0)
Requires-Dist: selenium (>=4.35.0,<5.0.0)
Project-URL: Documentation, https://github.com/johnazedo/financial-scraper/tree/main/docs
Project-URL: Repository, https://github.com/johnazedo/financial-scraper
